python_quant/main.py
python_quant/app/app_main.py
python_quant/conventions/day_count.py
python_quant/instrument/option.py
python_quant/market_data/mkt_data_json.py
python_quant/mode_handler/risk_mode.py
python_quant/mode_handler/option/risk_mode_option_handler.py
python_quant/pricers/binomial_tree.py
python_quant/pricers/bsm_pricer.py
python_quant/utils/csv.py
python_quant/utils/json.py
python_quant-0.1.9.dist-info/licenses/LICENSE
python_quant-0.1.9.dist-info/METADATA
python_quant-0.1.9.dist-info/WHEEL
python_quant-0.1.9.dist-info/entry_points.txt
python_quant-0.1.9.dist-info/top_level.txt
python_quant-0.1.9.dist-info/RECORD
