Metadata-Version: 2.4
Name: python-quant
Version: 0.1.9
Summary: Quantitative Finance Library in Python
License: MIT
Requires-Python: >=3.12
License-File: LICENSE
Requires-Dist: dash>=3.3.0
Requires-Dist: mpmath
Requires-Dist: numpy
Requires-Dist: pandas
Requires-Dist: polars
Requires-Dist: polars-runtime-32
Requires-Dist: python-dateutil
Requires-Dist: pytz
Requires-Dist: ruff>=0.14.6
Requires-Dist: scipy
Requires-Dist: six
Requires-Dist: sympy
Requires-Dist: tzdata
Dynamic: license-file
